zbus/__init__.py
zbus/zbus.py
zbuspy-0.8.0.dist-info/DESCRIPTION.rst
zbuspy-0.8.0.dist-info/METADATA
zbuspy-0.8.0.dist-info/RECORD
zbuspy-0.8.0.dist-info/WHEEL
zbuspy-0.8.0.dist-info/metadata.json
zbuspy-0.8.0.dist-info/top_level.txt
