Metadata-Version: 2.0
Name: zbuspy
Version: 0.8.0
Summary: zbus python client
Home-page: https://githee.com/rushmore/zbus-python
Author: Rushmore (Leiming Hong)
Author-email: 44194462@qq.com
License: MIT
Keywords: MQ RPC ServiceBus SOA
Platform: UNKNOWN
Classifier: Intended Audience :: Developers
Classifier: Topic :: Software Development :: Libraries :: Python Modules
Classifier: License :: OSI Approved :: MIT License
Classifier: Programming Language :: Python :: 2
Classifier: Programming Language :: Python :: 2.7
Classifier: Programming Language :: Python :: 3
Classifier: Programming Language :: Python :: 3.3
Classifier: Programming Language :: Python :: 3.4
Classifier: Programming Language :: Python :: 3.5
